frontend/index.html
frontend/assets/Docs-18879d0c.js
frontend/assets/Docs-faf41c00.css
frontend/assets/Home-0d76aebb.js
frontend/assets/Home-2789d9e5.css
frontend/assets/Results-30725ca6.css
frontend/assets/Results-cc2ccf3a.js
frontend/assets/Sidebar-540beee2.css
frontend/assets/Sidebar-ddd109a0.js
frontend/assets/UsePage-082bb9fa.js
frontend/assets/UsePage-e521c728.css
frontend/assets/axios-b5ee139b.js
frontend/assets/bean-20b95a41.gif
frontend/assets/index-428191b7.js
frontend/assets/index-5c5712a0.css
frontend/assets/logo2-5154ae89.js
frontend/assets/logo2-c8390092.svg
frontend/assets/set-1e4ecbe3.png
frontend/assets/weidu-072b2d88.png
src/cli/__init__.py
src/cli/cli.py
src/core/__init__.py
src/core/color_tree_new.py
src/core/content_restorer.py
src/core/dataset_processor.py
src/core/html_processor.py
src/core/llm_clean.py
src/core/llm_predictor.py
src/server/__init__.py
src/server/api/__init__.py
src/server/api/extract.py
src/server/api/extract_fixed.py
src/server/api/tasks.py
src/server/api/utils.py
src/server/models/__init__.py
src/server/models/schemas.py
src/server/services/__init__.py
src/server/services/extractor.py
src/server/services/task_manager.py
src/utils/tag_add.py
src/utils/url_fetcher.py
webis_llm-1.0.8.dist-info/METADATA
webis_llm-1.0.8.dist-info/WHEEL
webis_llm-1.0.8.dist-info/entry_points.txt
webis_llm-1.0.8.dist-info/top_level.txt
webis_llm-1.0.8.dist-info/RECORD
